crimson/file_loader/__init__.py
crimson/file_loader/converter.py
crimson/file_loader/utils.py
crimson_file_loader-0.1.5.dist-info/LICENSE
crimson_file_loader-0.1.5.dist-info/METADATA
crimson_file_loader-0.1.5.dist-info/WHEEL
crimson_file_loader-0.1.5.dist-info/top_level.txt
crimson_file_loader-0.1.5.dist-info/RECORD
