Metadata-Version: 2.1
Name: crimson-file-loader
Version: 0.1.5
Summary: Load files in one folder.
Author-email: Sisung Kim <sisung.kim1@gmail.com>
Project-URL: Homepage, https://github.com/crimson206/file-loader
Project-URL: Bug Tracker, https://github.com/crimson206/file-loader/issues
Classifier: Programming Language :: Python :: 3
Classifier: Intended Audience :: Developers
Classifier: Topic :: Software Development :: Build Tools
Classifier: License :: OSI Approved :: MIT License
Classifier: Operating System :: OS Independent
Requires-Python: >=3.9
License-File: LICENSE
Requires-Dist: pydantic
Requires-Dist: crimson-intelli-type==0.4.0
